autoemcee.py
autoemcee-0.2.0.dist-info/LICENSE
autoemcee-0.2.0.dist-info/METADATA
autoemcee-0.2.0.dist-info/WHEEL
autoemcee-0.2.0.dist-info/top_level.txt
autoemcee-0.2.0.dist-info/RECORD
